cimcb_lite/__init__.py
cimcb_lite/__version__.py
cimcb_lite/bootstrap/BC.py
cimcb_lite/bootstrap/BCA.py
cimcb_lite/bootstrap/BaseBootstrap.py
cimcb_lite/bootstrap/Perc.py
cimcb_lite/bootstrap/__init__.py
cimcb_lite/cross_val/BaseCrossVal.py
cimcb_lite/cross_val/__init__.py
cimcb_lite/cross_val/kfold.py
cimcb_lite/model/BaseModel.py
cimcb_lite/model/PLS_SIMPLS.py
cimcb_lite/model/__init__.py
cimcb_lite/plot/__init__.py
cimcb_lite/plot/boxplot.py
cimcb_lite/plot/distribution.py
cimcb_lite/plot/pca.py
cimcb_lite/plot/permutation_test.py
cimcb_lite/plot/roc.py
cimcb_lite/plot/scatter.py
cimcb_lite/plot/scatterCI.py
cimcb_lite/utils/__init__.py
cimcb_lite/utils/binary_metrics.py
cimcb_lite/utils/ci95_ellipse.py
cimcb_lite/utils/knnimpute.py
cimcb_lite/utils/load_dataXL.py
cimcb_lite/utils/nested_getattr.py
cimcb_lite/utils/scale.py
cimcb_lite/utils/table_check.py
cimcb_lite/utils/univariate_2class.py
cimcb_lite/utils/wmean.py
cimcb_lite-1.0.2.dist-info/LICENSE
cimcb_lite-1.0.2.dist-info/METADATA
cimcb_lite-1.0.2.dist-info/WHEEL
cimcb_lite-1.0.2.dist-info/top_level.txt
cimcb_lite-1.0.2.dist-info/RECORD
