Metadata-Version: 2.1
Name: cimcb-lite
Version: 1.0.2
Summary: A lite version of the cimcb package containing the necessary tools for the statistical analysis of untargeted and targeted metabolomics data.
Home-page: https://github.com/cimcb/cimcb_lite
Author: Kevin Mendez, David Broadhurst
Author-email: k.mendez@ecu.edu.au, d.broadhurst@ecu.edu.au
License: MIT License
Platform: UNKNOWN
Requires-Python: >=3.5
Requires-Dist: bokeh (>=1.0.0)
Requires-Dist: numpy
Requires-Dist: pandas
Requires-Dist: scipy
Requires-Dist: scikit-learn
Requires-Dist: statsmodels
Requires-Dist: tqdm
Requires-Dist: xlrd
